rtra_connector/__init__.py
rtra_connector/rtra_connector.py
HTLMSmall-0.1.0.dist-info/METADATA
HTLMSmall-0.1.0.dist-info/WHEEL
HTLMSmall-0.1.0.dist-info/top_level.txt
HTLMSmall-0.1.0.dist-info/RECORD
